eomap_models/__initi__.py
eomap_models/altimetry/__init__.py
eomap_models/altimetry/enums.py
eomap_models/altimetry/water_level.py
eomap_models/aoi.py
eomap_models/auth.py
eomap_models/general.py
eomap_models/scene.py
eomap_models/tile.py
eomap_models-0.1.15.dist-info/LICENSE
eomap_models-0.1.15.dist-info/WHEEL
eomap_models-0.1.15.dist-info/METADATA
eomap_models-0.1.15.dist-info/RECORD
