Metadata-Version: 2.1
Name: eomap-models
Version: 0.1.15
Summary: 
Author: Luis Coelho
Requires-Python: >=3.7,<4.0
Classifier: Programming Language :: Python :: 3
Classifier: Programming Language :: Python :: 3.10
Classifier: Programming Language :: Python :: 3.7
Classifier: Programming Language :: Python :: 3.8
Classifier: Programming Language :: Python :: 3.9
Requires-Dist: geojson-pydantic (==0.3.1)
Requires-Dist: pydantic[email] (>=1.9.1,<2.0.0)
